protonenv/__init__.py
protonenv/__version__.py
protonenv/cli_utils.py
protonenv/config.py
protonenv/core.py
protonenv/core_utils.py
protonenv/proton.json
protonenv/utils.py
protonenv-0.1.1.dist-info/LICENSE.md
protonenv-0.1.1.dist-info/METADATA
protonenv-0.1.1.dist-info/WHEEL
protonenv-0.1.1.dist-info/entry_points.txt
protonenv-0.1.1.dist-info/top_level.txt
protonenv-0.1.1.dist-info/RECORD
