Metadata-Version: 2.1
Name: protonenv
Version: 0.1.1
Summary: Simple Proton version and prefix management.
Home-page: https://github.com/rizkiarm/protonenv
Author: Muhammad Rizki Aulia Rahman Maulana
Author-email: rizki@rizkiarm.com
License: MIT
Keywords: steam,proton,prefix,wine
Platform: UNKNOWN
Classifier: License :: OSI Approved :: MIT License
Classifier: Programming Language :: Python :: 3
Classifier: Programming Language :: Python :: 3.6
Requires-Python: >=3.6.0
